[
  {
    "ApiId": "/providers/microsoft.powerapps/apis/shared_sharepointonline",
    "CdpRevision": {
      "BaseUrl": "/",
      "LastChangedTimeString": "2024-02-12T21:23:17.3090000Z",
      "RevisionNumber": 1
    },
    "ConnectedDataSourceInfoNameMapping": {
      "{Attachments}": "Attachments",
      "{Attachments}@odata.type": "{Attachments} ({Attachments}@odata.type)",
      "{FilenameWithExtension}": "File name with extension",
      "{FullPath}": "Full Path",
      "{HasAttachments}": "Has attachments",
      "{Identifier}": "Identifier",
      "{IsFolder}": "IsFolder",
      "{Link}": "Link to item",
      "{ModerationComment}": "Comments associated with the content approval of this list item",
      "{ModerationStatus}": "Content approval status",
      "{Name}": "Name",
      "{Path}": "Folder path",
      "{Thumbnail}": "Thumbnail",
      "{TriggerWindowEndToken}": "Trigger Window End Token",
      "{TriggerWindowStartToken}": "Trigger Window Start Token",
      "{VersionNumber}": "Version number",
      "ApplicantEmail": "ApplicantEmail",
      "Assigned": "Assigned",
      "Assigned#Claims": "Assigned Claims",
      "Author": "Created By",
      "Author#Claims": "Created By Claims",
      "Complete": "Complete",
      "ComplianceAssetId": "Compliance Asset Id",
      "Created": "Created",
      "DateRaised": "DateRaised",
      "Editor": "Modified By",
      "Editor#Claims": "Modified By Claims",
      "EmployeeType": "EmployeeType",
      "EmployeeType#Id": "EmployeeType Id",
      "EndDate": "EndDate",
      "FilterTag": "FilterTag",
      "FinalExtension": "FinalExtension",
      "FinalReview": "FinalReview",
      "FinalReviewDueDate": "FinalReviewDueDate",
      "FirstName": "FirstName",
      "HoursPerWeek": "HoursPerWeek",
      "ID": "ID",
      "InductionLog": "InductionLog",
      "InterimReview": "InterimReview",
      "InterimReviewDueDate": "InterimReviewDueDate",
      "ITAccount": "ITAccount",
      "ITAccountRef": "ITAccountRef",
      "ITLaptop": "ITLaptop",
      "ITLaptopRef": "ITLaptopRef",
      "ITMobile": "ITMobile",
      "ITMobileRef": "ITMobileRef",
      "ITSmartcard": "ITSmartcard",
      "ITSmartcardRef": "ITSmartcardRef",
      "JobTitle": "JobTitle",
      "LastName": "LastName",
      "LineManager": "LineManager",
      "LineManager#Claims": "LineManager Claims",
      "Modified": "Modified",
      "NewStarterApplicant": "NewStarterApplicant",
      "NewStarterHR": "NewStarterHR",
      "NewStarterLM": "NewStarterLM",
      "NominatedPerson": "NominatedPerson",
      "NominatedPerson#Claims": "NominatedPerson Claims",
      "OData__ColorTag": "Color Tag",
      "OData__x0034_GLaptop": "4GLaptop",
      "OData__x0034_GLaptopRef": "4GLaptopRef",
      "ProbationSignOff": "ProbationSignOff",
      "ReasonForNominatedPerson": "ReasonForNominatedPerson",
      "RequestType": "RequestType",
      "SalaryType": "SalaryType",
      "SalaryType#Id": "SalaryType Id",
      "Service": "Service",
      "Site": "Site",
      "Stage": "Stage",
      "Stage#Id": "Stage Id",
      "StartDate": "StartDate",
      "Team": "Team",
      "Title": "Title",
      "trac_application_id": "trac_application_id",
      "TracJobRef": "TracJobRef",
      "TriggerJob": "TriggerJob",
      "UID": "UID",
      "VRFID": "VRFID"
    },
    "DatasetName": "https://spectrumcic.sharepoint.com/sites/PowerAppsDevelopment",
    "EncodeDataset": true,
    "IsSampleData": false,
    "IsWritable": true,
    "Name": "Onboarding Record",
    "Type": "ConnectedDataSourceInfo"
  }
]